lendingclub2/__init__.py
lendingclub2/account.py
lendingclub2/authorization.py
lendingclub2/config.py
lendingclub2/error.py
lendingclub2/filter.py
lendingclub2/loan.py
lendingclub2/request.py
lendingclub2/utils.py
lendingclub2/response/__init__.py
lendingclub2/response/notes.py
lendingclub2/response/order.py
lendingclub2/response/portfolio.py
lendingclub2/response/summary.py
lendingclub2/response/transfer.py
lendingclub2-0.5.2.dist-info/LICENSE
lendingclub2-0.5.2.dist-info/METADATA
lendingclub2-0.5.2.dist-info/WHEEL
lendingclub2-0.5.2.dist-info/top_level.txt
lendingclub2-0.5.2.dist-info/RECORD
