Metadata-Version: 2.1
Name: lendingclub2
Version: 0.5.2
Summary: Help automating LendingClub processes
Home-page: https://github.com/ahartoto/lendingclub2
Author: Alex Hartoto
Author-email: ahartoto.dev@gmail.com
License: MIT
Keywords: lendingclub,lending-club,p2p,loan,api
Platform: UNKNOWN
Classifier: Development Status :: 2 - Pre-Alpha
Classifier: Environment :: Console
Classifier: Intended Audience :: Developers
Classifier: Intended Audience :: Education
Classifier: Intended Audience :: End Users/Desktop
Classifier: Intended Audience :: Information Technology
Classifier: License :: OSI Approved :: MIT License
Classifier: Operating System :: MacOS :: MacOS X
Classifier: Operating System :: POSIX :: Linux
Classifier: Programming Language :: Python
Classifier: Programming Language :: Python :: 3
Classifier: Programming Language :: Python :: 3.4
Classifier: Programming Language :: Python :: 3.5
Classifier: Programming Language :: Python :: 3.6
Classifier: Programming Language :: Python :: 3.7
Classifier: Topic :: Office/Business :: Financial
Requires-Dist: requests (>=2.21)
